phx_events/__init__.py
phx_events/async_logger.py
phx_events/client.py
phx_events/exceptions.py
phx_events/json_handler.py
phx_events/phx_messages.py
phx_events/topic_subscription.py
phx_events/utils.py
phx_events-0.4.1.dist-info/LICENSE
phx_events-0.4.1.dist-info/WHEEL
phx_events-0.4.1.dist-info/METADATA
phx_events-0.4.1.dist-info/RECORD
