Metadata-Version: 2.1
Name: phx-events
Version: 0.4.1
Summary: AsyncIO Phoenix Channels client for fast asynchronous message handling
Keywords: asyncio,channels,phoenix,websockets
Author-email: Jethro Muller <git@jethromuller.co.za>
Requires-Python: >=3.9,<4
Classifier: Development Status :: 3 - Alpha
Classifier: Environment :: Web Environment
Classifier: Framework :: AsyncIO
Classifier: Intended Audience :: Developers
Classifier: License :: OSI Approved :: Apache Software License
Classifier: Operating System :: OS Independent
Classifier: Programming Language :: Python :: 3 :: Only
Classifier: Programming Language :: Python :: 3.9
Requires-Dist: orjson ~= 3.6
Requires-Dist: websockets ~= 9.1
Project-URL: Documentation, https://acefire6.github.io/phx_events/
Project-URL: Source, https://github.com/AceFire6/phx_events/
